timestep/__init__.py
timestep/envs/__init__.py
timestep/envs/no_limit_texas_holdem/__init__.py
timestep/envs/no_limit_texas_holdem/env.py
timestep_envs_no_limit_texas_holdem-0.1.0.dist-info/LICENSE
timestep_envs_no_limit_texas_holdem-0.1.0.dist-info/METADATA
timestep_envs_no_limit_texas_holdem-0.1.0.dist-info/WHEEL
timestep_envs_no_limit_texas_holdem-0.1.0.dist-info/RECORD
