Metadata-Version: 2.1
Name: timestep-envs-no-limit-texas-holdem
Version: 0.1.0
Summary: 
Author: Michael Schock
Author-email: m@mjschock.com
Requires-Python: >=3.9,<4.0
Classifier: Programming Language :: Python :: 3
Classifier: Programming Language :: Python :: 3.9
Classifier: Programming Language :: Python :: 3.10
Classifier: Programming Language :: Python :: 3.11
Requires-Dist: langchain (>=0.0.173,<0.0.174)
Requires-Dist: pettingzoo[classic] (>=1.23.0,<2.0.0)
Requires-Dist: timestep-agents-action-mask-agent (>=0.1.0,<0.2.0)
